aws_request_signer/__init__.py
aws_request_signer/requests.py
aws_request_signer-1.1.1.dist-info/LICENSE
aws_request_signer-1.1.1.dist-info/WHEEL
aws_request_signer-1.1.1.dist-info/METADATA
aws_request_signer-1.1.1.dist-info/RECORD
