Metadata-Version: 2.1
Name: aws-request-signer
Version: 1.1.1
Summary: A python library to sign AWS requests using AWS Signature V4.
Home-page: https://www.github.com/iksteen/aws-request-signer
License: MIT
Author: Ingmar Steen
Author-email: iksteen@gmail.com
Requires-Python: >=3.6.1,<4.0.0
Classifier: License :: OSI Approved :: MIT License
Classifier: Programming Language :: Python :: 3
Classifier: Programming Language :: Python :: 3.10
Classifier: Programming Language :: Python :: 3.7
Classifier: Programming Language :: Python :: 3.8
Classifier: Programming Language :: Python :: 3.9
Provides-Extra: demo
Provides-Extra: requests
Requires-Dist: requests (>=2.21,<3.0); extra == "requests" or extra == "demo"
Requires-Dist: requests_toolbelt (>=0.8.0,<0.9.0); extra == "demo"
Project-URL: Repository, https://www.github.com/iksteen/aws-request-signer.git
